emotion_detection/__init__.py
emotion_detection/libNativeEmotionsLibrary.so
emotion_detection/cpp.cpython-37m-x86_64-linux-gnu.so
emotion_detection-0.0.1.dist-info/WHEEL
emotion_detection-0.0.1.dist-info/RECORD
emotion_detection-0.0.1.dist-info/top_level.txt
emotion_detection-0.0.1.dist-info/METADATA
