Metadata-Version: 2.1
Name: emotion-detection
Version: 0.0.1
Summary: Emotion Detection library from RealEyes
Home-page: https://developers.realeyesit.com/NEL/index.html
Author: Realeyes
Author-email: daniel@realeyesit.com
License: UNKNOWN
Platform: UNKNOWN
Requires-Dist: numpy >=1.10.0
